headline/__init__.py
headline/__main__.py
headline/_logger.py
headline/config.py
headline/io.py
headline/process.py
headline/sorters.py
headline/transform.py
headline/utils.py
headline/transformers/__init__.py
headline/transformers/func_transformers.py
headline/visitors/__init__.py
headline/visitors/func_visitors.py
headline-0.0.1.dist-info/LICENSE
headline-0.0.1.dist-info/METADATA
headline-0.0.1.dist-info/WHEEL
headline-0.0.1.dist-info/top_level.txt
headline-0.0.1.dist-info/RECORD
