Metadata-Version: 2.1
Name: headline
Version: 0.0.1
Summary: dynamically reorder functions
Author: ed cuss
Requires-Python: >=3.8
License-File: LICENSE
Requires-Dist: attrs
Requires-Dist: black >=24
Requires-Dist: isort
Requires-Dist: libcst
Requires-Dist: python-dotenv >=0.20.0
Provides-Extra: dev
Requires-Dist: headline[lint,test] ; extra == 'dev'
Provides-Extra: lint
Requires-Dist: pre-commit ; extra == 'lint'
Requires-Dist: ruff >=0.4.2 ; extra == 'lint'
Provides-Extra: test
Requires-Dist: pytest ; extra == 'test'
Requires-Dist: pytest-cov ; extra == 'test'
Requires-Dist: hypothesis ; extra == 'test'
